data_transformer/__init__.py
data_transformer/core/__init__.py
data_transformer/core/operations.py
data_transformer/core/transformer.py
data_transformer/examples/__init__.py
data_transformer/examples/advanced_usage.py
data_transformer/examples/basic_usage.py
data_transformer/tests/__init__.py
data_transformer/tests/test_transformer.py
data_transformer/utils/__init__.py
data_transformer/utils/helpers.py
data_transformer_toolkit-0.1.2.dist-info/LICENSE
data_transformer_toolkit-0.1.2.dist-info/METADATA
data_transformer_toolkit-0.1.2.dist-info/WHEEL
data_transformer_toolkit-0.1.2.dist-info/top_level.txt
data_transformer_toolkit-0.1.2.dist-info/RECORD
