Metadata-Version: 2.2
Name: data-transformer-toolkit
Version: 0.1.2
Summary: A lightweight solution for data transformation operations
Author: Vitoldas Vilkoicas
Author-email: vitoldas.vilkoicas@ktu.edu
Classifier: Programming Language :: Python :: 3
Classifier: License :: OSI Approved :: MIT License
Classifier: Operating System :: OS Independent
Requires-Python: >=3.6
License-File: LICENSE
Requires-Dist: pandas>=1.0.0
Requires-Dist: numpy>=1.18.0
Dynamic: author
Dynamic: author-email
Dynamic: classifier
Dynamic: description
Dynamic: description-content-type
Dynamic: requires-dist
Dynamic: requires-python
Dynamic: summary
